<?xml version="1.0" encoding="UTF-8" ?>
<templates xml:space="preserve">
    <t t-name="awesome_owl.playground">
        <div id="counter" class="p-3 border border-primary">
            hello world
            <Counter onChange.bind="incrementSum" />
            <Counter onChange.bind="incrementSum" />
            <div>The sum is: <t t-esc="sum.value"/></div>
        </div>
        <div>
            <Card title="'card 1'" content="this.str1"/>
            <Card title="'card 2'" content="this.str2"/>
        </div>
        <TodoList />
    </t>
</templates>
